{"GlobalPropertiesHash":"/8HJFjBejI3PmOYPnXng9G5Cu2BkZP8HqZPTJW/TERg=","FingerprintPatternsHash":"gq3WsqcKBUGTSNle7RKKyXRIwh7M8ccEqOqYvIzoM04=","PropertyOverridesHash":"8ZRc1sGeVrPBx4lD717BgRaQekyh78QKV9SKsdt638U=","InputHashes":["jmg3fOiBozxX0WvFwcyrPXkb4GJOxLZzSVG1Y5ckof8=","IAQMvufX2FlX26HBi7INU8aqdrMgIkP4g7vKDtxOMRI=","01UBBuFfxRT3Tg\u002BGd2OglJZHfOdBs8nMfxvO09MVu90=","qNFN5PE7Ca64IdLksWY5LGfM1GX5fBEfIzefcHjhY6o=","XHk6WdcLnTlYL0Q0\u002BoS8p1ArH4SMFOpGZtfkiIh2NEA=","6CnOJ/j6CtXNRKJVT2Lp2L4gDU8DNhSNdvO7gs6KouA="],"CachedAssets":{"IAQMvufX2FlX26HBi7INU8aqdrMgIkP4g7vKDtxOMRI=":{"Identity":"C:\\Users\\ASUS\\Desktop\\sertec-project_2026_04_21\\sertec-project\\SertecDashboard.Api\\wwwroot\\assets\\index-sf9UuhIj.css","SourceId":"SertecDashboard.Api","SourceType":"Discovered","ContentRoot":"C:\\Users\\ASUS\\Desktop\\sertec-project_2026_04_21\\sertec-project\\SertecDashboard.Api\\wwwroot\\","BasePath":"_content/SertecDashboard.Api","RelativePath":"assets/index-sf9UuhIj#[.{fingerprint}]?.css","AssetKind":"All","AssetMode":"All","AssetRole":"Primary","AssetMergeBehavior":null,"AssetMergeSource":"","RelatedAsset":null,"AssetTraitName":null,"AssetTraitValue":null,"Fingerprint":"cwybeaph0h","Integrity":"bIsYFpUPWaUwi1Q33z1iNKbH2E\u002BCtUwLpvOis9zK5eI=","CopyToOutputDirectory":"Never","CopyToPublishDirectory":"PreserveNewest","OriginalItemSpec":"wwwroot\\assets\\index-sf9UuhIj.css","FileLength":67209,"LastWriteTime":"2026-05-04T12:20:32.0200728+00:00"},"01UBBuFfxRT3Tg\u002BGd2OglJZHfOdBs8nMfxvO09MVu90=":{"Identity":"C:\\Users\\ASUS\\Desktop\\sertec-project_2026_04_21\\sertec-project\\SertecDashboard.Api\\wwwroot\\index.html","SourceId":"SertecDashboard.Api","SourceType":"Discovered","ContentRoot":"C:\\Users\\ASUS\\Desktop\\sertec-project_2026_04_21\\sertec-project\\SertecDashboard.Api\\wwwroot\\","BasePath":"_content/SertecDashboard.Api","RelativePath":"index#[.{fingerprint}]?.html","AssetKind":"All","AssetMode":"All","AssetRole":"Primary","AssetMergeBehavior":null,"AssetMergeSource":"","RelatedAsset":null,"AssetTraitName":null,"AssetTraitValue":null,"Fingerprint":"v7u8dm7zz7","Integrity":"\u002B7/Y0RBqBf16CC6Gf8vNJcAYvlj4Uu2yBCT3hBSMGok=","CopyToOutputDirectory":"Never","CopyToPublishDirectory":"PreserveNewest","OriginalItemSpec":"wwwroot\\index.html","FileLength":650,"LastWriteTime":"2026-05-04T12:20:32.0200728+00:00"},"jmg3fOiBozxX0WvFwcyrPXkb4GJOxLZzSVG1Y5ckof8=":{"Identity":"C:\\Users\\ASUS\\Desktop\\sertec-project_2026_04_21\\sertec-project\\SertecDashboard.Api\\wwwroot\\assets\\index-B2lmfSxy.js","SourceId":"SertecDashboard.Api","SourceType":"Discovered","ContentRoot":"C:\\Users\\ASUS\\Desktop\\sertec-project_2026_04_21\\sertec-project\\SertecDashboard.Api\\wwwroot\\","BasePath":"_content/SertecDashboard.Api","RelativePath":"assets/index-B2lmfSxy#[.{fingerprint}]?.js","AssetKind":"All","AssetMode":"All","AssetRole":"Primary","AssetMergeBehavior":null,"AssetMergeSource":"","RelatedAsset":null,"AssetTraitName":null,"AssetTraitValue":null,"Fingerprint":"8ay9ko4ywq","Integrity":"MDZQ9f/GTBmJKT6iVbd6lCpwZePu2ZmFsHJF2hAd6TA=","CopyToOutputDirectory":"Never","CopyToPublishDirectory":"PreserveNewest","OriginalItemSpec":"wwwroot\\assets\\index-B2lmfSxy.js","FileLength":303858,"LastWriteTime":"2026-05-04T12:20:32.0200728+00:00"}},"CachedCopyCandidates":{}}